<?xml version='1.0' encoding='UTF-8' standalone='no'?>
<!-- Created by minerva version 13.2.0 on 2019-09-05 at 10:53:48 CEST with JSBML version 1.4. -->
<sbml xmlns="http://www.sbml.org/sbml/level3/version2/core" layout:required="false" level="3" multi:required="true" render:required="false" version="2" xmlns:layout="http://www.sbml.org/sbml/level3/version1/layout/version1" xmlns:multi="http://www.sbml.org/sbml/level3/version1/multi/version1" xmlns:render="http://www.sbml.org/sbml/level3/version1/render/version1">
  <model areaUnits="area_unit" extentUnits="mole" lengthUnits="metre" substanceUnits="mole" timeUnits="second" volumeUnits="litre">
    <notes>
      <body xmlns="http://www.w3.org/1999/xhtml">
     <p/>
  </body>
    </notes>
    <annotation>
      <rdf:RDF xmlns:rdf="http://www.w3.org/1999/02/22-rdf-syntax-ns#" xmlns:dc="http://purl.org/dc/elements/1.1/" xmlns:dcterms="http://purl.org/dc/terms/" xmlns:vCard="http://www.w3.org/2001/vcard-rdf/3.0#" xmlns:bqbiol="http://biomodels.net/biology-qualifiers/" xmlns:bqmodel="http://biomodels.net/model-qualifiers/">
<rdf:Description rdf:about="#">
<dcterms:modified rdf:parseType="Resource"/>
</rdf:Description>
</rdf:RDF>
    </annotation>
      <layout:listOfLayouts xmlns:layout="http://www.sbml.org/sbml/level3/version1/layout/version1" xmlns:xsi="http://www.w3.org/2001/XMLSchema-instance">
      <layout:layout layout:id="minerva_layout">
        <render:listOfRenderInformation xmlns:render="http://www.sbml.org/sbml/level3/version1/render/version1">
          <render:renderInformation render:id="minerva_definitions">
            <render:listOfColorDefinitions>
              <render:colorDefinition render:id="color_FFFFFFFF" render:value="#FFFFFFFF"/>
              <render:colorDefinition render:id="color_FF000000" render:value="#000000FF"/>
            </render:listOfColorDefinitions>
            <render:listOfLineEndings>
              <render:lineEnding render:id="line_ending_NONE">
                <render:g/>
              </render:lineEnding>
              <render:lineEnding render:id="line_ending_FULL">
                <layout:boundingBox>
                  <layout:position layout:x="-12" layout:y="-6" layout:z="12"/>
                  <layout:dimensions layout:height="0" layout:width="12"/>
                </layout:boundingBox>
                <render:g render:fill="color_FF000000">
                  <render:polygon>
                    <render:listOfElements>
                      <render:element render:x="0%" render:y="0%" xsi:type="RenderPoint"/>
                      <render:element render:x="100%" render:y="50%" xsi:type="RenderPoint"/>
                      <render:element render:x="0%" render:y="100%" xsi:type="RenderPoint"/>
                      <render:element render:x="0%" render:y="0%" xsi:type="RenderPoint"/>
                    </render:listOfElements>
                  </render:polygon>
                </render:g>
              </render:lineEnding>
              <render:lineEnding render:id="line_ending_BLANK">
                <layout:boundingBox>
                  <layout:position layout:x="-12" layout:y="-6" layout:z="12"/>
                  <layout:dimensions layout:height="0" layout:width="12"/>
                </layout:boundingBox>
                <render:g render:fill="color_FFFFFFFF">
                  <render:polygon>
                    <render:listOfElements>
                      <render:element render:x="0%" render:y="0%" xsi:type="RenderPoint"/>
                      <render:element render:x="100%" render:y="50%" xsi:type="RenderPoint"/>
                      <render:element render:x="0%" render:y="100%" xsi:type="RenderPoint"/>
                      <render:element render:x="0%" render:y="0%" xsi:type="RenderPoint"/>
                    </render:listOfElements>
                  </render:polygon>
                </render:g>
              </render:lineEnding>
              <render:lineEnding render:id="line_ending_CIRCLE">
                <layout:boundingBox>
                  <layout:position layout:x="-2" layout:y="0" layout:z="4"/>
                  <layout:dimensions layout:height="0" layout:width="4"/>
                </layout:boundingBox>
                <render:g render:fill="color_FFFFFFFF">
                  <render:ellipse render:cx="0%" render:cy="0%" render:rx="4" render:ry="4"/>
                </render:g>
              </render:lineEnding>
            </render:listOfLineEndings>
            <render:listOfStyles>
              <render:style render:idList="glyph_n1">
                <render:g render:fill="color_FFFFFFFF" render:font-size="12" render:stroke-width="1.0">
                  <render:rectangle render:height="100%" render:rx="0%" render:ry="0%" render:stroke="color_FF000000" render:width="100%" render:x="0%" render:y="0%"/>
                </render:g>
              </render:style>
              <render:style render:idList="text_glyph_n1">
                <render:g render:text-anchor="middle" render:vtext-anchor="middle"/>
              </render:style>
              <render:style render:idList="glyph_n3">
                <render:g render:fill="color_FFFFFFFF" render:font-size="12" render:stroke-width="1.0">
                  <render:ellipse render:cx="50%" render:cy="50%" render:rx="50%" render:ry="50%" render:stroke="color_FF000000"/>
                </render:g>
              </render:style>
              <render:style render:idList="text_glyph_n3">
                <render:g render:text-anchor="middle" render:vtext-anchor="middle"/>
              </render:style>
              <render:style render:idList="glyph_n9">
                <render:g render:fill="color_FFFFFFFF" render:font-size="12" render:stroke-width="1.0">
                  <render:rectangle render:height="100%" render:rx="0%" render:ry="0%" render:stroke="color_FF000000" render:width="100%" render:x="0%" render:y="0%"/>
                </render:g>
              </render:style>
              <render:style render:idList="text_glyph_n9">
                <render:g render:text-anchor="middle" render:vtext-anchor="middle"/>
              </render:style>
              <render:style render:idList="glyph_n8">
                <render:g render:fill="color_FFFFFFFF" render:font-size="12" render:stroke-width="1.0">
                  <render:ellipse render:cx="50%" render:cy="50%" render:rx="50%" render:ry="50%" render:stroke="color_FF000000"/>
                </render:g>
              </render:style>
              <render:style render:idList="text_glyph_n8">
                <render:g render:text-anchor="middle" render:vtext-anchor="middle"/>
              </render:style>
              <render:style render:idList="glyph_n14">
                <render:g render:fill="color_FFFFFFFF" render:font-size="12" render:stroke-width="1.0">
                  <render:rectangle render:height="100%" render:rx="0%" render:ry="0%" render:stroke="color_FF000000" render:width="100%" render:x="0%" render:y="0%"/>
                </render:g>
              </render:style>
              <render:style render:idList="text_glyph_n14">
                <render:g render:text-anchor="middle" render:vtext-anchor="middle"/>
              </render:style>
              <render:style render:idList="glyph_n0">
                <render:g render:fill="color_FFFFFFFF" render:font-size="12" render:stroke-width="1.0">
                  <render:ellipse render:cx="50%" render:cy="50%" render:rx="50%" render:ry="50%" render:stroke="color_FF000000"/>
                </render:g>
              </render:style>
              <render:style render:idList="text_glyph_n0">
                <render:g render:text-anchor="middle" render:vtext-anchor="middle"/>
              </render:style>
              <render:style render:idList="glyph_n20">
                <render:g render:fill="color_FFFFFFFF" render:font-size="12" render:stroke-width="1.0">
                  <render:rectangle render:height="100%" render:rx="0%" render:ry="0%" render:stroke="color_FF000000" render:width="100%" render:x="0%" render:y="0%"/>
                </render:g>
              </render:style>
              <render:style render:idList="text_glyph_n20">
                <render:g render:text-anchor="middle" render:vtext-anchor="middle"/>
              </render:style>
              <render:style render:idList="glyph_n4">
                <render:g render:fill="color_FFFFFFFF" render:font-size="12" render:stroke-width="1.0">
                  <render:rectangle render:height="100%" render:rx="0%" render:ry="0%" render:stroke="color_FF000000" render:width="100%" render:x="0%" render:y="0%"/>
                </render:g>
              </render:style>
              <render:style render:idList="text_glyph_n4">
                <render:g render:text-anchor="middle" render:vtext-anchor="middle"/>
              </render:style>
              <render:style render:idList="glyph_n10">
                <render:g render:fill="color_FFFFFFFF" render:font-size="12" render:stroke-width="1.0">
                  <render:rectangle render:height="100%" render:rx="0%" render:ry="0%" render:stroke="color_FF000000" render:width="100%" render:x="0%" render:y="0%"/>
                </render:g>
              </render:style>
              <render:style render:idList="text_glyph_n10">
                <render:g render:text-anchor="middle" render:vtext-anchor="middle"/>
              </render:style>
              <render:style render:idList="glyph_n16">
                <render:g render:fill="color_FFFFFFFF" render:font-size="12" render:stroke-width="1.0">
                  <render:rectangle render:height="100%" render:rx="0%" render:ry="0%" render:stroke="color_FF000000" render:width="100%" render:x="0%" render:y="0%"/>
                </render:g>
              </render:style>
              <render:style render:idList="text_glyph_n16">
                <render:g render:text-anchor="middle" render:vtext-anchor="middle"/>
              </render:style>
              <render:style render:idList="glyph_n2">
                <render:g render:fill="color_FFFFFFFF" render:font-size="12" render:stroke-width="1.0">
                  <render:ellipse render:cx="50%" render:cy="50%" render:rx="50%" render:ry="50%" render:stroke="color_FF000000"/>
                </render:g>
              </render:style>
              <render:style render:idList="text_glyph_n2">
                <render:g render:text-anchor="middle" render:vtext-anchor="middle"/>
              </render:style>
              <render:style render:idList="glyph_n11">
                <render:g render:fill="color_FFFFFFFF" render:font-size="12" render:stroke-width="1.0">
                  <render:ellipse render:cx="50%" render:cy="50%" render:rx="50%" render:ry="50%" render:stroke="color_FF000000"/>
                </render:g>
              </render:style>
              <render:style render:idList="text_glyph_n11">
                <render:g render:text-anchor="middle" render:vtext-anchor="middle"/>
              </render:style>
              <render:style render:idList="node_1">
                <render:g render:endHead="line_ending_NONE" render:fill="color_FF000000" render:stroke="color_FF000000" render:stroke-width="1.0"/>
              </render:style>
              <render:style render:idList="node_2">
                <render:g render:endHead="line_ending_FULL" render:fill="color_FF000000" render:stroke="color_FF000000" render:stroke-width="1.0"/>
              </render:style>
              <render:style render:idList="node_3">
                <render:g render:endHead="line_ending_BLANK" render:fill="color_FF000000" render:stroke="color_FF000000" render:stroke-width="1.0"/>
              </render:style>
              <render:style render:idList="glyph_n21_0">
                <render:g render:fill="color_FF000000" render:stroke="color_FF000000" render:stroke-width="1.0"/>
              </render:style>
              <render:style render:idList="node_5">
                <render:g render:endHead="line_ending_NONE" render:fill="color_FF000000" render:stroke="color_FF000000" render:stroke-width="1.0"/>
              </render:style>
              <render:style render:idList="node_6">
                <render:g render:endHead="line_ending_FULL" render:fill="color_FF000000" render:stroke="color_FF000000" render:stroke-width="1.0"/>
              </render:style>
              <render:style render:idList="node_7">
                <render:g render:endHead="line_ending_CIRCLE" render:fill="color_FF000000" render:stroke="color_FF000000" render:stroke-width="1.0"/>
              </render:style>
              <render:style render:idList="glyph_n15_4">
                <render:g render:fill="color_FF000000" render:stroke="color_FF000000" render:stroke-width="1.0"/>
              </render:style>
              <render:style render:idList="node_9">
                <render:g render:endHead="line_ending_FULL" render:fill="color_FF000000" render:stroke="color_FF000000" render:stroke-width="1.0"/>
              </render:style>
              <render:style render:idList="node_10">
                <render:g render:endHead="line_ending_FULL" render:fill="color_FF000000" render:stroke="color_FF000000" render:stroke-width="1.0"/>
              </render:style>
              <render:style render:idList="node_11">
                <render:g render:endHead="line_ending_CIRCLE" render:fill="color_FF000000" render:stroke="color_FF000000" render:stroke-width="1.0"/>
              </render:style>
              <render:style render:idList="glyph_n5_8">
                <render:g render:fill="color_FF000000" render:stroke="color_FF000000" render:stroke-width="1.0"/>
              </render:style>
              <render:style render:idList="node_13">
                <render:g render:endHead="line_ending_NONE" render:fill="color_FF000000" render:stroke="color_FF000000" render:stroke-width="1.0"/>
              </render:style>
              <render:style render:idList="node_14">
                <render:g render:endHead="line_ending_FULL" render:fill="color_FF000000" render:stroke="color_FF000000" render:stroke-width="1.0"/>
              </render:style>
              <render:style render:idList="node_15">
                <render:g render:endHead="line_ending_CIRCLE" render:fill="color_FF000000" render:stroke="color_FF000000" render:stroke-width="1.0"/>
              </render:style>
              <render:style render:idList="glyph_n13_12">
                <render:g render:fill="color_FF000000" render:stroke="color_FF000000" render:stroke-width="1.0"/>
              </render:style>
              <render:style render:idList="node_17">
                <render:g render:endHead="line_ending_NONE" render:fill="color_FF000000" render:stroke="color_FF000000" render:stroke-width="1.0"/>
              </render:style>
              <render:style render:idList="node_18">
                <render:g render:endHead="line_ending_FULL" render:fill="color_FF000000" render:stroke="color_FF000000" render:stroke-width="1.0"/>
              </render:style>
              <render:style render:idList="node_19">
                <render:g render:endHead="line_ending_CIRCLE" render:fill="color_FF000000" render:stroke="color_FF000000" render:stroke-width="1.0"/>
              </render:style>
              <render:style render:idList="glyph_n6_16">
                <render:g render:fill="color_FF000000" render:stroke="color_FF000000" render:stroke-width="1.0"/>
              </render:style>
              <render:style render:idList="node_21">
                <render:g render:endHead="line_ending_NONE" render:fill="color_FF000000" render:stroke="color_FF000000" render:stroke-width="1.0"/>
              </render:style>
              <render:style render:idList="node_22">
                <render:g render:endHead="line_ending_FULL" render:fill="color_FF000000" render:stroke="color_FF000000" render:stroke-width="1.0"/>
              </render:style>
              <render:style render:idList="node_23">
                <render:g render:endHead="line_ending_CIRCLE" render:fill="color_FF000000" render:stroke="color_FF000000" render:stroke-width="1.0"/>
              </render:style>
              <render:style render:idList="glyph_n12_20">
                <render:g render:fill="color_FF000000" render:stroke="color_FF000000" render:stroke-width="1.0"/>
              </render:style>
              <render:style render:idList="node_25">
                <render:g render:endHead="line_ending_NONE" render:fill="color_FF000000" render:stroke="color_FF000000" render:stroke-width="1.0"/>
              </render:style>
              <render:style render:idList="node_26">
                <render:g render:endHead="line_ending_FULL" render:fill="color_FF000000" render:stroke="color_FF000000" render:stroke-width="1.0"/>
              </render:style>
              <render:style render:idList="node_27">
                <render:g render:endHead="line_ending_CIRCLE" render:fill="color_FF000000" render:stroke="color_FF000000" render:stroke-width="1.0"/>
              </render:style>
              <render:style render:idList="glyph_n7_24">
                <render:g render:fill="color_FF000000" render:stroke="color_FF000000" render:stroke-width="1.0"/>
              </render:style>
            </render:listOfStyles>
          </render:renderInformation>
        </render:listOfRenderInformation>
        <layout:dimensions layout:height="456.1134033203125" layout:width="742.7318725585938"/>
        <layout:listOfAdditionalGraphicalObjects>
          <layout:generalGlyph layout:id="modification_1054" layout:reference="modification_residue_0">
            <layout:boundingBox>
              <layout:position layout:x="602.7318725585939" layout:y="237.5350341796875" layout:z="15"/>
              <layout:dimensions layout:height="12" layout:width="12"/>
            </layout:boundingBox>
            <layout:listOfReferenceGlyphs>
              <layout:referenceGlyph layout:glyph="glyph_n14" layout:id="modification_reference_1055">
                <layout:boundingBox>
                  <layout:position layout:x="602.7318725585939" layout:y="237.5350341796875" layout:z="15"/>
                  <layout:dimensions layout:height="12" layout:width="12"/>
                </layout:boundingBox>
              </layout:referenceGlyph>
            </layout:listOfReferenceGlyphs>
          </layout:generalGlyph>
          <layout:generalGlyph layout:id="modification_1056" layout:reference="modification_residue_1">
            <layout:boundingBox>
              <layout:position layout:x="602.7318725585938" layout:y="367.5350341796875" layout:z="16"/>
              <layout:dimensions layout:height="12" layout:width="12"/>
            </layout:boundingBox>
            <layout:listOfReferenceGlyphs>
              <layout:referenceGlyph layout:glyph="glyph_n16" layout:id="modification_reference_1057">
                <layout:boundingBox>
                  <layout:position layout:x="602.7318725585938" layout:y="367.5350341796875" layout:z="16"/>
                  <layout:dimensions layout:height="12" layout:width="12"/>
                </layout:boundingBox>
              </layout:referenceGlyph>
            </layout:listOfReferenceGlyphs>
          </layout:generalGlyph>
        </layout:listOfAdditionalGraphicalObjects>
        <layout:listOfCompartmentGlyphs>
          <layout:compartmentGlyph layout:compartment="default" layout:id="default_compartment">
            <layout:boundingBox>
              <layout:position layout:x="0" layout:y="0" layout:z="0"/>
              <layout:dimensions layout:height="456.1134033203125" layout:width="742.7318725585938"/>
            </layout:boundingBox>
          </layout:compartmentGlyph>
        </layout:listOfCompartmentGlyphs>
        <layout:listOfSpeciesGlyphs>
          <layout:speciesGlyph layout:id="glyph_n1" layout:species="species_0">
            <layout:boundingBox>
              <layout:position layout:x="662.7318725585938" layout:y="268.5350341796875" layout:z="12"/>
              <layout:dimensions layout:height="40" layout:width="80"/>
            </layout:boundingBox>
          </layout:speciesGlyph>
          <layout:speciesGlyph layout:id="glyph_n3" layout:species="species_1">
            <layout:boundingBox>
              <layout:position layout:x="75" layout:y="272.5350341796875" layout:z="10"/>
              <layout:dimensions layout:height="32" layout:width="140"/>
            </layout:boundingBox>
          </layout:speciesGlyph>
          <layout:speciesGlyph layout:id="glyph_n9" layout:species="species_2">
            <layout:boundingBox>
              <layout:position layout:x="0" layout:y="333.5350341796875" layout:z="18"/>
              <layout:dimensions layout:height="40" layout:width="80"/>
            </layout:boundingBox>
          </layout:speciesGlyph>
          <layout:speciesGlyph layout:id="glyph_n8" layout:species="species_3">
            <layout:boundingBox>
              <layout:position layout:x="75" layout:y="402.5350341796875" layout:z="11"/>
              <layout:dimensions layout:height="32" layout:width="140"/>
            </layout:boundingBox>
          </layout:speciesGlyph>
          <layout:speciesGlyph layout:id="glyph_n14" layout:species="species_4">
            <layout:boundingBox>
              <layout:position layout:x="544.7318725585938" layout:y="203.5350341796875" layout:z="14"/>
              <layout:dimensions layout:height="40" layout:width="80"/>
            </layout:boundingBox>
          </layout:speciesGlyph>
          <layout:speciesGlyph layout:id="glyph_n0" layout:species="species_5">
            <layout:boundingBox>
              <layout:position layout:x="554.7318725585938" layout:y="88.5350341796875" layout:z="19"/>
              <layout:dimensions layout:height="32" layout:width="60"/>
            </layout:boundingBox>
          </layout:speciesGlyph>
          <layout:speciesGlyph layout:id="glyph_n20" layout:species="species_6">
            <layout:boundingBox>
              <layout:position layout:x="662.7318725585938" layout:y="21.578369140625" layout:z="16"/>
              <layout:dimensions layout:height="40" layout:width="80"/>
            </layout:boundingBox>
          </layout:speciesGlyph>
          <layout:speciesGlyph layout:id="glyph_n4" layout:species="species_7">
            <layout:boundingBox>
              <layout:position layout:x="0" layout:y="203.5350341796875" layout:z="17"/>
              <layout:dimensions layout:height="40" layout:width="80"/>
            </layout:boundingBox>
          </layout:speciesGlyph>
          <layout:speciesGlyph layout:id="glyph_n10" layout:species="species_8">
            <layout:boundingBox>
              <layout:position layout:x="210" layout:y="333.5350341796875" layout:z="13"/>
              <layout:dimensions layout:height="40" layout:width="80"/>
            </layout:boundingBox>
          </layout:speciesGlyph>
          <layout:speciesGlyph layout:id="glyph_n16" layout:species="species_9">
            <layout:boundingBox>
              <layout:position layout:x="544.7318725585938" layout:y="333.5350341796875" layout:z="15"/>
              <layout:dimensions layout:height="40" layout:width="80"/>
            </layout:boundingBox>
          </layout:speciesGlyph>
          <layout:speciesGlyph layout:id="glyph_n2" layout:species="species_10">
            <layout:boundingBox>
              <layout:position layout:x="75" layout:y="142.5350341796875" layout:z="9"/>
              <layout:dimensions layout:height="32" layout:width="140"/>
            </layout:boundingBox>
          </layout:speciesGlyph>
          <layout:speciesGlyph layout:id="glyph_n11" layout:species="species_11">
            <layout:boundingBox>
              <layout:position layout:x="363.4999694824219" layout:y="272.5350341796875" layout:z="8"/>
              <layout:dimensions layout:height="32" layout:width="140"/>
            </layout:boundingBox>
          </layout:speciesGlyph>
        </layout:listOfSpeciesGlyphs>
        <layout:listOfReactionGlyphs>
          <layout:reactionGlyph layout:id="glyph_n21_0" layout:reaction="glyph_n21">
            <layout:boundingBox>
              <layout:position layout:z="4"/>
            </layout:boundingBox>
            <layout:curve/>
            <layout:listOfSpeciesReferenceGlyphs>
              <layout:speciesReferenceGlyph layout:id="node_1" layout:role="substrate" layout:speciesGlyph="glyph_n20">
                <layout:curve>
                  <layout:listOfCurveSegments>
                    <layout:curveSegment xsi:type="LineSegment">
                      <layout:start layout:x="702.7318725585938" layout:y="104.5350341796875"/>
                      <layout:end layout:x="702.7318725585938" layout:y="85.9100341796875"/>
                    </layout:curveSegment>
                    <layout:curveSegment xsi:type="LineSegment">
                      <layout:start layout:x="702.7318725585938" layout:y="85.9100341796875"/>
                      <layout:end layout:x="702.7318725585938" layout:y="62.078369140625"/>
                    </layout:curveSegment>
                  </layout:listOfCurveSegments>
                </layout:curve>
              </layout:speciesReferenceGlyph>
              <layout:speciesReferenceGlyph layout:id="node_2" layout:role="product" layout:speciesGlyph="glyph_n1">
                <layout:curve>
                  <layout:listOfCurveSegments>
                    <layout:curveSegment xsi:type="LineSegment">
                      <layout:start layout:x="702.7318725585938" layout:y="104.5350341796875"/>
                      <layout:end layout:x="702.7318725585938" layout:y="123.1600341796875"/>
                    </layout:curveSegment>
                    <layout:curveSegment xsi:type="LineSegment">
                      <layout:start layout:x="702.7318725585938" layout:y="123.1600341796875"/>
                      <layout:end layout:x="702.7318725585938" layout:y="264.9100341796875"/>
                    </layout:curveSegment>
                  </layout:listOfCurveSegments>
                </layout:curve>
              </layout:speciesReferenceGlyph>
              <layout:speciesReferenceGlyph layout:id="node_3" layout:role="modifier" layout:speciesGlyph="glyph_n0">
                <layout:curve>
                  <layout:listOfCurveSegments>
                    <layout:curveSegment xsi:type="LineSegment">
                      <layout:start layout:x="615.7318725585938" layout:y="104.5350341796875"/>
                      <layout:end layout:x="697.7318725585938" layout:y="104.5350341796875"/>
                    </layout:curveSegment>
                  </layout:listOfCurveSegments>
                </layout:curve>
              </layout:speciesReferenceGlyph>
            </layout:listOfSpeciesReferenceGlyphs>
          </layout:reactionGlyph>
          <layout:reactionGlyph layout:id="glyph_n15_4" layout:reaction="glyph_n15">
            <layout:boundingBox>
              <layout:position layout:z="3"/>
            </layout:boundingBox>
            <layout:curve/>
            <layout:listOfSpeciesReferenceGlyphs>
              <layout:speciesReferenceGlyph layout:id="node_5" layout:role="substrate" layout:speciesGlyph="glyph_n14">
                <layout:curve>
                  <layout:listOfCurveSegments>
                    <layout:curveSegment xsi:type="LineSegment">
                      <layout:start layout:x="584.7318725585938" layout:y="288.5350341796875"/>
                      <layout:end layout:x="584.7318725585938" layout:y="269.9100341796875"/>
                    </layout:curveSegment>
                    <layout:curveSegment xsi:type="LineSegment">
                      <layout:start layout:x="584.7318725585938" layout:y="269.9100341796875"/>
                      <layout:end layout:x="584.7318725585938" layout:y="244.0350341796875"/>
                    </layout:curveSegment>
                  </layout:listOfCurveSegments>
                </layout:curve>
              </layout:speciesReferenceGlyph>
              <layout:speciesReferenceGlyph layout:id="node_6" layout:role="product" layout:speciesGlyph="glyph_n16">
                <layout:curve>
                  <layout:listOfCurveSegments>
                    <layout:curveSegment xsi:type="LineSegment">
                      <layout:start layout:x="584.7318725585938" layout:y="288.5350341796875"/>
                      <layout:end layout:x="584.7318725585938" layout:y="307.1600341796875"/>
                    </layout:curveSegment>
                    <layout:curveSegment xsi:type="LineSegment">
                      <layout:start layout:x="584.7318725585938" layout:y="307.1600341796875"/>
                      <layout:end layout:x="584.7318725585938" layout:y="329.9100341796875"/>
                    </layout:curveSegment>
                  </layout:listOfCurveSegments>
                </layout:curve>
              </layout:speciesReferenceGlyph>
              <layout:speciesReferenceGlyph layout:id="node_7" layout:role="modifier" layout:speciesGlyph="glyph_n1">
                <layout:curve>
                  <layout:listOfCurveSegments>
                    <layout:curveSegment xsi:type="LineSegment">
                      <layout:start layout:x="662.2318725585938" layout:y="288.5350341796875"/>
                      <layout:end layout:x="589.7318725585938" layout:y="288.5350341796875"/>
                    </layout:curveSegment>
                  </layout:listOfCurveSegments>
                </layout:curve>
              </layout:speciesReferenceGlyph>
            </layout:listOfSpeciesReferenceGlyphs>
          </layout:reactionGlyph>
          <layout:reactionGlyph layout:id="glyph_n5_8" layout:reaction="glyph_n5">
            <layout:boundingBox>
              <layout:position layout:z="5"/>
            </layout:boundingBox>
            <layout:curve/>
            <layout:listOfSpeciesReferenceGlyphs>
              <layout:speciesReferenceGlyph layout:id="node_9" layout:role="substrate" layout:speciesGlyph="glyph_n2">
                <layout:curve>
                  <layout:listOfCurveSegments>
                    <layout:curveSegment xsi:type="LineSegment">
                      <layout:start layout:x="145" layout:y="223.5350341796875"/>
                      <layout:end layout:x="145" layout:y="204.9100341796875"/>
                    </layout:curveSegment>
                    <layout:curveSegment xsi:type="LineSegment">
                      <layout:start layout:x="145" layout:y="204.9100341796875"/>
                      <layout:end layout:x="145" layout:y="178.6600341796875"/>
                    </layout:curveSegment>
                  </layout:listOfCurveSegments>
                </layout:curve>
              </layout:speciesReferenceGlyph>
              <layout:speciesReferenceGlyph layout:id="node_10" layout:role="product" layout:speciesGlyph="glyph_n3">
                <layout:curve>
                  <layout:listOfCurveSegments>
                    <layout:curveSegment xsi:type="LineSegment">
                      <layout:start layout:x="145" layout:y="223.5350341796875"/>
                      <layout:end layout:x="145" layout:y="242.1600341796875"/>
                    </layout:curveSegment>
                    <layout:curveSegment xsi:type="LineSegment">
                      <layout:start layout:x="145" layout:y="242.1600341796875"/>
                      <layout:end layout:x="145" layout:y="268.4100341796875"/>
                    </layout:curveSegment>
                  </layout:listOfCurveSegments>
                </layout:curve>
              </layout:speciesReferenceGlyph>
              <layout:speciesReferenceGlyph layout:id="node_11" layout:role="modifier" layout:speciesGlyph="glyph_n4">
                <layout:curve>
                  <layout:listOfCurveSegments>
                    <layout:curveSegment xsi:type="LineSegment">
                      <layout:start layout:x="80.5" layout:y="223.5350341796875"/>
                      <layout:end layout:x="140" layout:y="223.5350341796875"/>
                    </layout:curveSegment>
                  </layout:listOfCurveSegments>
                </layout:curve>
              </layout:speciesReferenceGlyph>
            </layout:listOfSpeciesReferenceGlyphs>
          </layout:reactionGlyph>
          <layout:reactionGlyph layout:id="glyph_n13_12" layout:reaction="glyph_n13">
            <layout:boundingBox>
              <layout:position layout:z="2"/>
            </layout:boundingBox>
            <layout:curve/>
            <layout:listOfSpeciesReferenceGlyphs>
              <layout:speciesReferenceGlyph layout:id="node_13" layout:role="substrate" layout:speciesGlyph="glyph_n11">
                <layout:curve>
                  <layout:listOfCurveSegments>
                    <layout:curveSegment xsi:type="LineSegment">
                      <layout:start layout:x="308.70654296875" layout:y="299.6102294921875"/>
                      <layout:end layout:x="327.33154296875" layout:y="299.6102294921875"/>
                    </layout:curveSegment>
                    <layout:curveSegment xsi:type="LineSegment">
                      <layout:start layout:x="327.33154296875" layout:y="299.6102294921875"/>
                      <layout:end layout:x="366.92596435546875" layout:y="294.443359375"/>
                    </layout:curveSegment>
                  </layout:listOfCurveSegments>
                </layout:curve>
              </layout:speciesReferenceGlyph>
              <layout:speciesReferenceGlyph layout:id="node_14" layout:role="product" layout:speciesGlyph="glyph_n3">
                <layout:curve>
                  <layout:listOfCurveSegments>
                    <layout:curveSegment xsi:type="LineSegment">
                      <layout:start layout:x="308.70654296875" layout:y="299.6102294921875"/>
                      <layout:end layout:x="290.08154296875" layout:y="299.6102294921875"/>
                    </layout:curveSegment>
                    <layout:curveSegment xsi:type="LineSegment">
                      <layout:start layout:x="290.08154296875" layout:y="299.6102294921875"/>
                      <layout:end layout:x="216.44290161132812" layout:y="293.36834716796875"/>
                    </layout:curveSegment>
                  </layout:listOfCurveSegments>
                </layout:curve>
              </layout:speciesReferenceGlyph>
              <layout:speciesReferenceGlyph layout:id="node_15" layout:role="modifier" layout:speciesGlyph="glyph_n16">
                <layout:curve>
                  <layout:listOfCurveSegments>
                    <layout:curveSegment xsi:type="LineSegment">
                      <layout:start layout:x="544.2318725585938" layout:y="353.5350341796875"/>
                      <layout:end layout:x="308.70654296875" layout:y="353.5350341796875"/>
                    </layout:curveSegment>
                    <layout:curveSegment xsi:type="LineSegment">
                      <layout:start layout:x="308.70654296875" layout:y="353.5350341796875"/>
                      <layout:end layout:x="308.70654296875" layout:y="304.6102294921875"/>
                    </layout:curveSegment>
                  </layout:listOfCurveSegments>
                </layout:curve>
              </layout:speciesReferenceGlyph>
            </layout:listOfSpeciesReferenceGlyphs>
          </layout:reactionGlyph>
          <layout:reactionGlyph layout:id="glyph_n6_16" layout:reaction="glyph_n6">
            <layout:boundingBox>
              <layout:position layout:z="6"/>
            </layout:boundingBox>
            <layout:curve/>
            <layout:listOfSpeciesReferenceGlyphs>
              <layout:speciesReferenceGlyph layout:id="node_17" layout:role="substrate" layout:speciesGlyph="glyph_n3">
                <layout:curve>
                  <layout:listOfCurveSegments>
                    <layout:curveSegment xsi:type="LineSegment">
                      <layout:start layout:x="163" layout:y="353.5350341796875"/>
                      <layout:end layout:x="163" layout:y="334.9100341796875"/>
                    </layout:curveSegment>
                    <layout:curveSegment xsi:type="LineSegment">
                      <layout:start layout:x="163" layout:y="334.9100341796875"/>
                      <layout:end layout:x="149.69737243652344" layout:y="305.4977722167969"/>
                    </layout:curveSegment>
                  </layout:listOfCurveSegments>
                </layout:curve>
              </layout:speciesReferenceGlyph>
              <layout:speciesReferenceGlyph layout:id="node_18" layout:role="product" layout:speciesGlyph="glyph_n8">
                <layout:curve>
                  <layout:listOfCurveSegments>
                    <layout:curveSegment xsi:type="LineSegment">
                      <layout:start layout:x="163" layout:y="353.5350341796875"/>
                      <layout:end layout:x="163" layout:y="372.1600341796875"/>
                    </layout:curveSegment>
                    <layout:curveSegment xsi:type="LineSegment">
                      <layout:start layout:x="163" layout:y="372.1600341796875"/>
                      <layout:end layout:x="150.5313720703125" layout:y="398.56060791015625"/>
                    </layout:curveSegment>
                  </layout:listOfCurveSegments>
                </layout:curve>
              </layout:speciesReferenceGlyph>
              <layout:speciesReferenceGlyph layout:id="node_19" layout:role="modifier" layout:speciesGlyph="glyph_n10">
                <layout:curve>
                  <layout:listOfCurveSegments>
                    <layout:curveSegment xsi:type="LineSegment">
                      <layout:start layout:x="209.5" layout:y="353.5350341796875"/>
                      <layout:end layout:x="168" layout:y="353.5350341796875"/>
                    </layout:curveSegment>
                  </layout:listOfCurveSegments>
                </layout:curve>
              </layout:speciesReferenceGlyph>
            </layout:listOfSpeciesReferenceGlyphs>
          </layout:reactionGlyph>
          <layout:reactionGlyph layout:id="glyph_n12_20" layout:reaction="glyph_n12">
            <layout:boundingBox>
              <layout:position layout:z="1"/>
            </layout:boundingBox>
            <layout:curve/>
            <layout:listOfSpeciesReferenceGlyphs>
              <layout:speciesReferenceGlyph layout:id="node_21" layout:role="substrate" layout:speciesGlyph="glyph_n3">
                <layout:curve>
                  <layout:listOfCurveSegments>
                    <layout:curveSegment xsi:type="LineSegment">
                      <layout:start layout:x="308.70654296875" layout:y="274.04486083984375"/>
                      <layout:end layout:x="290.08154296875" layout:y="274.04486083984375"/>
                    </layout:curveSegment>
                    <layout:curveSegment xsi:type="LineSegment">
                      <layout:start layout:x="290.08154296875" layout:y="274.04486083984375"/>
                      <layout:end layout:x="211.5952911376953" layout:y="282.6404724121094"/>
                    </layout:curveSegment>
                  </layout:listOfCurveSegments>
                </layout:curve>
              </layout:speciesReferenceGlyph>
              <layout:speciesReferenceGlyph layout:id="node_22" layout:role="product" layout:speciesGlyph="glyph_n11">
                <layout:curve>
                  <layout:listOfCurveSegments>
                    <layout:curveSegment xsi:type="LineSegment">
                      <layout:start layout:x="308.70654296875" layout:y="274.04486083984375"/>
                      <layout:end layout:x="327.33154296875" layout:y="274.04486083984375"/>
                    </layout:curveSegment>
                    <layout:curveSegment xsi:type="LineSegment">
                      <layout:start layout:x="327.33154296875" layout:y="274.04486083984375"/>
                      <layout:end layout:x="366.51141357421875" layout:y="280.75677490234375"/>
                    </layout:curveSegment>
                  </layout:listOfCurveSegments>
                </layout:curve>
              </layout:speciesReferenceGlyph>
              <layout:speciesReferenceGlyph layout:id="node_23" layout:role="modifier" layout:speciesGlyph="glyph_n14">
                <layout:curve>
                  <layout:listOfCurveSegments>
                    <layout:curveSegment xsi:type="LineSegment">
                      <layout:start layout:x="544.2318725585938" layout:y="223.5350341796875"/>
                      <layout:end layout:x="308.70654296875" layout:y="223.5350341796875"/>
                    </layout:curveSegment>
                    <layout:curveSegment xsi:type="LineSegment">
                      <layout:start layout:x="308.70654296875" layout:y="223.5350341796875"/>
                      <layout:end layout:x="308.70654296875" layout:y="269.04486083984375"/>
                    </layout:curveSegment>
                  </layout:listOfCurveSegments>
                </layout:curve>
              </layout:speciesReferenceGlyph>
            </layout:listOfSpeciesReferenceGlyphs>
          </layout:reactionGlyph>
          <layout:reactionGlyph layout:id="glyph_n7_24" layout:reaction="glyph_n7">
            <layout:boundingBox>
              <layout:position layout:z="7"/>
            </layout:boundingBox>
            <layout:curve/>
            <layout:listOfSpeciesReferenceGlyphs>
              <layout:speciesReferenceGlyph layout:id="node_25" layout:role="substrate" layout:speciesGlyph="glyph_n8">
                <layout:curve>
                  <layout:listOfCurveSegments>
                    <layout:curveSegment xsi:type="LineSegment">
                      <layout:start layout:x="127" layout:y="353.5350341796875"/>
                      <layout:end layout:x="127" layout:y="372.1600341796875"/>
                    </layout:curveSegment>
                    <layout:curveSegment xsi:type="LineSegment">
                      <layout:start layout:x="127" layout:y="372.1600341796875"/>
                      <layout:end layout:x="140.30262756347656" layout:y="401.572265625"/>
                    </layout:curveSegment>
                  </layout:listOfCurveSegments>
                </layout:curve>
              </layout:speciesReferenceGlyph>
              <layout:speciesReferenceGlyph layout:id="node_26" layout:role="product" layout:speciesGlyph="glyph_n3">
                <layout:curve>
                  <layout:listOfCurveSegments>
                    <layout:curveSegment xsi:type="LineSegment">
                      <layout:start layout:x="127" layout:y="353.5350341796875"/>
                      <layout:end layout:x="127" layout:y="334.9100341796875"/>
                    </layout:curveSegment>
                    <layout:curveSegment xsi:type="LineSegment">
                      <layout:start layout:x="127" layout:y="334.9100341796875"/>
                      <layout:end layout:x="139.4686279296875" layout:y="308.5094299316406"/>
                    </layout:curveSegment>
                  </layout:listOfCurveSegments>
                </layout:curve>
              </layout:speciesReferenceGlyph>
              <layout:speciesReferenceGlyph layout:id="node_27" layout:role="modifier" layout:speciesGlyph="glyph_n9">
                <layout:curve>
                  <layout:listOfCurveSegments>
                    <layout:curveSegment xsi:type="LineSegment">
                      <layout:start layout:x="80.5" layout:y="353.5350341796875"/>
                      <layout:end layout:x="122" layout:y="353.5350341796875"/>
                    </layout:curveSegment>
                  </layout:listOfCurveSegments>
                </layout:curve>
              </layout:speciesReferenceGlyph>
            </layout:listOfSpeciesReferenceGlyphs>
          </layout:reactionGlyph>
        </layout:listOfReactionGlyphs>
        <layout:listOfTextGlyphs>
          <layout:textGlyph layout:id="text_glyph_n1" layout:originOfText="glyph_n1" layout:text="PKA">
            <layout:boundingBox>
              <layout:position layout:x="662.7318725585938" layout:y="268.5350341796875" layout:z="13"/>
              <layout:dimensions layout:height="40" layout:width="80"/>
            </layout:boundingBox>
          </layout:textGlyph>
          <layout:textGlyph layout:id="text_glyph_n3" layout:originOfText="glyph_n3" layout:text="?-D-fructose-6P">
            <layout:boundingBox>
              <layout:position layout:x="75" layout:y="272.5350341796875" layout:z="11"/>
              <layout:dimensions layout:height="32" layout:width="140"/>
            </layout:boundingBox>
          </layout:textGlyph>
          <layout:textGlyph layout:id="text_glyph_n9" layout:originOfText="glyph_n9" layout:text="F1,6BP">
            <layout:boundingBox>
              <layout:position layout:x="0" layout:y="333.5350341796875" layout:z="19"/>
              <layout:dimensions layout:height="40" layout:width="80"/>
            </layout:boundingBox>
          </layout:textGlyph>
          <layout:textGlyph layout:id="text_glyph_n8" layout:originOfText="glyph_n8" layout:text="?-D-fructose-1,6P2">
            <layout:boundingBox>
              <layout:position layout:x="75" layout:y="402.5350341796875" layout:z="12"/>
              <layout:dimensions layout:height="32" layout:width="140"/>
            </layout:boundingBox>
          </layout:textGlyph>
          <layout:textGlyph layout:id="text_glyph_n14" layout:originOfText="glyph_n14" layout:text="PFKFB2">
            <layout:boundingBox>
              <layout:position layout:x="544.7318725585938" layout:y="203.5350341796875" layout:z="15"/>
              <layout:dimensions layout:height="40" layout:width="80"/>
            </layout:boundingBox>
          </layout:textGlyph>
          <layout:textGlyph layout:id="text_glyph_n0" layout:originOfText="glyph_n0" layout:text="cAMP">
            <layout:boundingBox>
              <layout:position layout:x="554.7318725585938" layout:y="88.5350341796875" layout:z="20"/>
              <layout:dimensions layout:height="32" layout:width="60"/>
            </layout:boundingBox>
          </layout:textGlyph>
          <layout:textGlyph layout:id="text_glyph_n20" layout:originOfText="glyph_n20" layout:text="PKA">
            <layout:boundingBox>
              <layout:position layout:x="662.7318725585938" layout:y="21.578369140625" layout:z="17"/>
              <layout:dimensions layout:height="40" layout:width="80"/>
            </layout:boundingBox>
          </layout:textGlyph>
          <layout:textGlyph layout:id="text_glyph_n4" layout:originOfText="glyph_n4" layout:text="GPI">
            <layout:boundingBox>
              <layout:position layout:x="0" layout:y="203.5350341796875" layout:z="18"/>
              <layout:dimensions layout:height="40" layout:width="80"/>
            </layout:boundingBox>
          </layout:textGlyph>
          <layout:textGlyph layout:id="text_glyph_n10" layout:originOfText="glyph_n10" layout:text="PFK1">
            <layout:boundingBox>
              <layout:position layout:x="210" layout:y="333.5350341796875" layout:z="14"/>
              <layout:dimensions layout:height="40" layout:width="80"/>
            </layout:boundingBox>
          </layout:textGlyph>
          <layout:textGlyph layout:id="text_glyph_n16" layout:originOfText="glyph_n16" layout:text="PFKFB2">
            <layout:boundingBox>
              <layout:position layout:x="544.7318725585938" layout:y="333.5350341796875" layout:z="16"/>
              <layout:dimensions layout:height="40" layout:width="80"/>
            </layout:boundingBox>
          </layout:textGlyph>
          <layout:textGlyph layout:id="text_glyph_n2" layout:originOfText="glyph_n2" layout:text="?-D-glucose-6P">
            <layout:boundingBox>
              <layout:position layout:x="75" layout:y="142.5350341796875" layout:z="10"/>
              <layout:dimensions layout:height="32" layout:width="140"/>
            </layout:boundingBox>
          </layout:textGlyph>
          <layout:textGlyph layout:id="text_glyph_n11" layout:originOfText="glyph_n11" layout:text="?-D-fructose-2,6P2">
            <layout:boundingBox>
              <layout:position layout:x="363.4999694824219" layout:y="272.5350341796875" layout:z="9"/>
              <layout:dimensions layout:height="32" layout:width="140"/>
            </layout:boundingBox>
          </layout:textGlyph>
        </layout:listOfTextGlyphs>
      </layout:layout>
    </layout:listOfLayouts>
    <multi:listOfSpeciesTypes xmlns:multi="http://www.sbml.org/sbml/level3/version1/multi/version1">
      <multi:speciesType multi:id="minerva_species_type_GenericProtein" multi:name="GenericProtein" sboTerm="SBO:0000252">
        <multi:listOfSpeciesFeatureTypes>
          <multi:speciesFeatureType multi:id="minerva_structural_state_GenericProtein" multi:name="Structural state" multi:occur="1">
            <multi:listOfPossibleSpeciesFeatureValues>
              <multi:possibleSpeciesFeatureValue multi:id="minerva_structural_state_GenericProtein_1045"/>
              <multi:possibleSpeciesFeatureValue multi:id="minerva_structural_state_GenericProtein_1046" multi:name="active"/>
              <multi:possibleSpeciesFeatureValue multi:id="minerva_structural_state_GenericProtein_1052" multi:name="inactive"/>
            </multi:listOfPossibleSpeciesFeatureValues>
          </multi:speciesFeatureType>
          <multi:speciesFeatureType multi:id="minerva_position_to_compartment_GenericProtein" multi:name="Position to compartment" multi:occur="1">
            <multi:listOfPossibleSpeciesFeatureValues>
              <multi:possibleSpeciesFeatureValue multi:id="minerva_position_to_compartment_GenericProtein_1047" multi:name="NULL"/>
            </multi:listOfPossibleSpeciesFeatureValues>
          </multi:speciesFeatureType>
          <multi:speciesFeatureType multi:id="minerva_activity_GenericProtein" multi:name="Activity" multi:occur="1">
            <multi:listOfPossibleSpeciesFeatureValues>
              <multi:possibleSpeciesFeatureValue multi:id="minerva_activity_GenericProtein_1048" multi:name="false"/>
            </multi:listOfPossibleSpeciesFeatureValues>
          </multi:speciesFeatureType>
          <multi:speciesFeatureType multi:id="minerva_modification_type_GenericProtein_Residue_null" multi:occur="1">
            <multi:listOfPossibleSpeciesFeatureValues>
              <multi:possibleSpeciesFeatureValue multi:id="minerva_modification_type_GenericProtein_Residue_null_1051" multi:name="S36"/>
            </multi:listOfPossibleSpeciesFeatureValues>
          </multi:speciesFeatureType>
          <multi:speciesFeatureType multi:id="minerva_modification_type_GenericProtein_Residue_PHOSPHORYLATED" multi:name="phosphorylated" multi:occur="1">
            <multi:listOfPossibleSpeciesFeatureValues>
              <multi:possibleSpeciesFeatureValue multi:id="minerva_modification_type_GenericProtein_Residue_PHOSPHORYLATED_1053" multi:name="S36"/>
            </multi:listOfPossibleSpeciesFeatureValues>
          </multi:speciesFeatureType>
        </multi:listOfSpeciesFeatureTypes>
      </multi:speciesType>
      <multi:speciesType multi:id="minerva_species_type_SimpleMolecule" multi:name="SimpleMolecule" sboTerm="SBO:0000247">
        <multi:listOfSpeciesFeatureTypes>
          <multi:speciesFeatureType multi:id="minerva_position_to_compartment_SimpleMolecule" multi:name="Position to compartment" multi:occur="1">
            <multi:listOfPossibleSpeciesFeatureValues>
              <multi:possibleSpeciesFeatureValue multi:id="minerva_position_to_compartment_SimpleMolecule_1049" multi:name="NULL"/>
            </multi:listOfPossibleSpeciesFeatureValues>
          </multi:speciesFeatureType>
          <multi:speciesFeatureType multi:id="minerva_activity_SimpleMolecule" multi:name="Activity" multi:occur="1">
            <multi:listOfPossibleSpeciesFeatureValues>
              <multi:possibleSpeciesFeatureValue multi:id="minerva_activity_SimpleMolecule_1050" multi:name="false"/>
            </multi:listOfPossibleSpeciesFeatureValues>
          </multi:speciesFeatureType>
        </multi:listOfSpeciesFeatureTypes>
      </multi:speciesType>
    </multi:listOfSpeciesTypes>
    <listOfUnitDefinitions>
      <unitDefinition id="area_unit" name="area">
        <listOfUnits>
          <unit exponent="2" kind="metre" multiplier="1" scale="0"/>
        </listOfUnits>
      </unitDefinition>
    </listOfUnitDefinitions>
    <listOfCompartments>
      <compartment constant="false" id="default" multi:isType="false" size="1" spatialDimensions="3">
        <notes>
          <body xmlns="http://www.w3.org/1999/xhtml">
     <p/>
  </body>
        </notes>
        <annotation>
          <rdf:RDF xmlns:rdf="http://www.w3.org/1999/02/22-rdf-syntax-ns#" xmlns:dc="http://purl.org/dc/elements/1.1/" xmlns:dcterms="http://purl.org/dc/terms/" xmlns:vCard="http://www.w3.org/2001/vcard-rdf/3.0#" xmlns:bqbiol="http://biomodels.net/biology-qualifiers/" xmlns:bqmodel="http://biomodels.net/model-qualifiers/">
<rdf:Description rdf:about="#">
<dcterms:modified rdf:parseType="Resource"/>
</rdf:Description>
</rdf:RDF>
        </annotation>
            </compartment>
    </listOfCompartments>
    <listOfSpecies>
      <species boundaryCondition="false" compartment="default" constant="false" hasOnlySubstanceUnits="false" id="species_0" initialConcentration="0" multi:speciesType="minerva_species_type_GenericProtein" name="PKA" sboTerm="SBO:0000252">
        <notes>
          <body xmlns="http://www.w3.org/1999/xhtml">
     <p/>
  </body>
        </notes>
        <annotation>
          <rdf:RDF xmlns:rdf="http://www.w3.org/1999/02/22-rdf-syntax-ns#" xmlns:dc="http://purl.org/dc/elements/1.1/" xmlns:dcterms="http://purl.org/dc/terms/" xmlns:vCard="http://www.w3.org/2001/vcard-rdf/3.0#" xmlns:bqbiol="http://biomodels.net/biology-qualifiers/" xmlns:bqmodel="http://biomodels.net/model-qualifiers/">
<rdf:Description rdf:about="#">
<dcterms:modified rdf:parseType="Resource"/>
</rdf:Description>
</rdf:RDF>
        </annotation>
              <multi:listOfSpeciesFeatures>
          <multi:speciesFeature xmlns:multi="http://www.sbml.org/sbml/level3/version1/multi/version1" multi:occur="1" multi:speciesFeatureType="minerva_structural_state_GenericProtein">
            <multi:listOfSpeciesFeatureValues>
              <multi:speciesFeatureValue multi:value="minerva_structural_state_GenericProtein_1046"/>
            </multi:listOfSpeciesFeatureValues>
          </multi:speciesFeature>
          <multi:speciesFeature xmlns:multi="http://www.sbml.org/sbml/level3/version1/multi/version1" multi:occur="1" multi:speciesFeatureType="minerva_position_to_compartment_GenericProtein">
            <multi:listOfSpeciesFeatureValues>
              <multi:speciesFeatureValue multi:value="minerva_position_to_compartment_GenericProtein_1047"/>
            </multi:listOfSpeciesFeatureValues>
          </multi:speciesFeature>
          <multi:speciesFeature xmlns:multi="http://www.sbml.org/sbml/level3/version1/multi/version1" multi:occur="1" multi:speciesFeatureType="minerva_activity_GenericProtein">
            <multi:listOfSpeciesFeatureValues>
              <multi:speciesFeatureValue multi:value="minerva_activity_GenericProtein_1048"/>
            </multi:listOfSpeciesFeatureValues>
          </multi:speciesFeature>
        </multi:listOfSpeciesFeatures>
      </species>
      <species boundaryCondition="false" compartment="default" constant="false" hasOnlySubstanceUnits="false" id="species_1" initialConcentration="0" multi:speciesType="minerva_species_type_SimpleMolecule" name="?-D-fructose-6P" sboTerm="SBO:0000247">
        <notes>
          <body xmlns="http://www.w3.org/1999/xhtml">
     <p/>
  </body>
        </notes>
        <annotation>
          <rdf:RDF xmlns:rdf="http://www.w3.org/1999/02/22-rdf-syntax-ns#" xmlns:dc="http://purl.org/dc/elements/1.1/" xmlns:dcterms="http://purl.org/dc/terms/" xmlns:vCard="http://www.w3.org/2001/vcard-rdf/3.0#" xmlns:bqbiol="http://biomodels.net/biology-qualifiers/" xmlns:bqmodel="http://biomodels.net/model-qualifiers/">
<rdf:Description rdf:about="#">
<dcterms:modified rdf:parseType="Resource"/>
</rdf:Description>
</rdf:RDF>
        </annotation>
              <multi:listOfSpeciesFeatures>
          <multi:speciesFeature xmlns:multi="http://www.sbml.org/sbml/level3/version1/multi/version1" multi:occur="1" multi:speciesFeatureType="minerva_position_to_compartment_SimpleMolecule">
            <multi:listOfSpeciesFeatureValues>
              <multi:speciesFeatureValue multi:value="minerva_position_to_compartment_SimpleMolecule_1049"/>
            </multi:listOfSpeciesFeatureValues>
          </multi:speciesFeature>
          <multi:speciesFeature xmlns:multi="http://www.sbml.org/sbml/level3/version1/multi/version1" multi:occur="1" multi:speciesFeatureType="minerva_activity_SimpleMolecule">
            <multi:listOfSpeciesFeatureValues>
              <multi:speciesFeatureValue multi:value="minerva_activity_SimpleMolecule_1050"/>
            </multi:listOfSpeciesFeatureValues>
          </multi:speciesFeature>
        </multi:listOfSpeciesFeatures>
      </species>
      <species boundaryCondition="false" compartment="default" constant="false" hasOnlySubstanceUnits="false" id="species_2" initialConcentration="0" multi:speciesType="minerva_species_type_GenericProtein" name="F1,6BP" sboTerm="SBO:0000252">
        <notes>
          <body xmlns="http://www.w3.org/1999/xhtml">
     <p/>
  </body>
        </notes>
        <annotation>
          <rdf:RDF xmlns:rdf="http://www.w3.org/1999/02/22-rdf-syntax-ns#" xmlns:dc="http://purl.org/dc/elements/1.1/" xmlns:dcterms="http://purl.org/dc/terms/" xmlns:vCard="http://www.w3.org/2001/vcard-rdf/3.0#" xmlns:bqbiol="http://biomodels.net/biology-qualifiers/" xmlns:bqmodel="http://biomodels.net/model-qualifiers/">
<rdf:Description rdf:about="#">
<dcterms:modified rdf:parseType="Resource"/>
</rdf:Description>
</rdf:RDF>
        </annotation>
              <multi:listOfSpeciesFeatures>
          <multi:speciesFeature xmlns:multi="http://www.sbml.org/sbml/level3/version1/multi/version1" multi:occur="1" multi:speciesFeatureType="minerva_position_to_compartment_GenericProtein">
            <multi:listOfSpeciesFeatureValues>
              <multi:speciesFeatureValue multi:value="minerva_position_to_compartment_GenericProtein_1047"/>
            </multi:listOfSpeciesFeatureValues>
          </multi:speciesFeature>
          <multi:speciesFeature xmlns:multi="http://www.sbml.org/sbml/level3/version1/multi/version1" multi:occur="1" multi:speciesFeatureType="minerva_activity_GenericProtein">
            <multi:listOfSpeciesFeatureValues>
              <multi:speciesFeatureValue multi:value="minerva_activity_GenericProtein_1048"/>
            </multi:listOfSpeciesFeatureValues>
          </multi:speciesFeature>
        </multi:listOfSpeciesFeatures>
      </species>
      <species boundaryCondition="false" compartment="default" constant="false" hasOnlySubstanceUnits="false" id="species_3" initialConcentration="0" multi:speciesType="minerva_species_type_SimpleMolecule" name="?-D-fructose-1,6P2" sboTerm="SBO:0000247">
        <notes>
          <body xmlns="http://www.w3.org/1999/xhtml">
     <p/>
  </body>
        </notes>
        <annotation>
          <rdf:RDF xmlns:rdf="http://www.w3.org/1999/02/22-rdf-syntax-ns#" xmlns:dc="http://purl.org/dc/elements/1.1/" xmlns:dcterms="http://purl.org/dc/terms/" xmlns:vCard="http://www.w3.org/2001/vcard-rdf/3.0#" xmlns:bqbiol="http://biomodels.net/biology-qualifiers/" xmlns:bqmodel="http://biomodels.net/model-qualifiers/">
<rdf:Description rdf:about="#">
<dcterms:modified rdf:parseType="Resource"/>
</rdf:Description>
</rdf:RDF>
        </annotation>
              <multi:listOfSpeciesFeatures>
          <multi:speciesFeature xmlns:multi="http://www.sbml.org/sbml/level3/version1/multi/version1" multi:occur="1" multi:speciesFeatureType="minerva_position_to_compartment_SimpleMolecule">
            <multi:listOfSpeciesFeatureValues>
              <multi:speciesFeatureValue multi:value="minerva_position_to_compartment_SimpleMolecule_1049"/>
            </multi:listOfSpeciesFeatureValues>
          </multi:speciesFeature>
          <multi:speciesFeature xmlns:multi="http://www.sbml.org/sbml/level3/version1/multi/version1" multi:occur="1" multi:speciesFeatureType="minerva_activity_SimpleMolecule">
            <multi:listOfSpeciesFeatureValues>
              <multi:speciesFeatureValue multi:value="minerva_activity_SimpleMolecule_1050"/>
            </multi:listOfSpeciesFeatureValues>
          </multi:speciesFeature>
        </multi:listOfSpeciesFeatures>
      </species>
      <species boundaryCondition="false" compartment="default" constant="false" hasOnlySubstanceUnits="false" id="species_4" initialConcentration="0" multi:speciesType="minerva_species_type_GenericProtein" name="PFKFB2" sboTerm="SBO:0000252">
        <notes>
          <body xmlns="http://www.w3.org/1999/xhtml">
     <p/>
  </body>
        </notes>
        <annotation>
          <rdf:RDF xmlns:rdf="http://www.w3.org/1999/02/22-rdf-syntax-ns#" xmlns:dc="http://purl.org/dc/elements/1.1/" xmlns:dcterms="http://purl.org/dc/terms/" xmlns:vCard="http://www.w3.org/2001/vcard-rdf/3.0#" xmlns:bqbiol="http://biomodels.net/biology-qualifiers/" xmlns:bqmodel="http://biomodels.net/model-qualifiers/">
<rdf:Description rdf:about="#">
<dcterms:modified rdf:parseType="Resource"/>
</rdf:Description>
</rdf:RDF>
        </annotation>
              <multi:listOfSpeciesFeatures>
          <multi:speciesFeature xmlns:multi="http://www.sbml.org/sbml/level3/version1/multi/version1" multi:occur="1" multi:speciesFeatureType="minerva_position_to_compartment_GenericProtein">
            <multi:listOfSpeciesFeatureValues>
              <multi:speciesFeatureValue multi:value="minerva_position_to_compartment_GenericProtein_1047"/>
            </multi:listOfSpeciesFeatureValues>
          </multi:speciesFeature>
          <multi:speciesFeature xmlns:multi="http://www.sbml.org/sbml/level3/version1/multi/version1" multi:occur="1" multi:speciesFeatureType="minerva_modification_type_GenericProtein_Residue_null">
            <multi:listOfSpeciesFeatureValues>
              <multi:speciesFeatureValue id="modification_residue_0" multi:value="minerva_modification_type_GenericProtein_Residue_null_1051"/>
            </multi:listOfSpeciesFeatureValues>
          </multi:speciesFeature>
          <multi:speciesFeature xmlns:multi="http://www.sbml.org/sbml/level3/version1/multi/version1" multi:occur="1" multi:speciesFeatureType="minerva_activity_GenericProtein">
            <multi:listOfSpeciesFeatureValues>
              <multi:speciesFeatureValue multi:value="minerva_activity_GenericProtein_1048"/>
            </multi:listOfSpeciesFeatureValues>
          </multi:speciesFeature>
        </multi:listOfSpeciesFeatures>
      </species>
      <species boundaryCondition="false" compartment="default" constant="false" hasOnlySubstanceUnits="false" id="species_5" initialConcentration="0" multi:speciesType="minerva_species_type_SimpleMolecule" name="cAMP" sboTerm="SBO:0000247">
        <notes>
          <body xmlns="http://www.w3.org/1999/xhtml">
     <p/>
  </body>
        </notes>
        <annotation>
          <rdf:RDF xmlns:rdf="http://www.w3.org/1999/02/22-rdf-syntax-ns#" xmlns:dc="http://purl.org/dc/elements/1.1/" xmlns:dcterms="http://purl.org/dc/terms/" xmlns:vCard="http://www.w3.org/2001/vcard-rdf/3.0#" xmlns:bqbiol="http://biomodels.net/biology-qualifiers/" xmlns:bqmodel="http://biomodels.net/model-qualifiers/">
<rdf:Description rdf:about="#">
<dcterms:modified rdf:parseType="Resource"/>
</rdf:Description>
</rdf:RDF>
        </annotation>
              <multi:listOfSpeciesFeatures>
          <multi:speciesFeature xmlns:multi="http://www.sbml.org/sbml/level3/version1/multi/version1" multi:occur="1" multi:speciesFeatureType="minerva_position_to_compartment_SimpleMolecule">
            <multi:listOfSpeciesFeatureValues>
              <multi:speciesFeatureValue multi:value="minerva_position_to_compartment_SimpleMolecule_1049"/>
            </multi:listOfSpeciesFeatureValues>
          </multi:speciesFeature>
          <multi:speciesFeature xmlns:multi="http://www.sbml.org/sbml/level3/version1/multi/version1" multi:occur="1" multi:speciesFeatureType="minerva_activity_SimpleMolecule">
            <multi:listOfSpeciesFeatureValues>
              <multi:speciesFeatureValue multi:value="minerva_activity_SimpleMolecule_1050"/>
            </multi:listOfSpeciesFeatureValues>
          </multi:speciesFeature>
        </multi:listOfSpeciesFeatures>
      </species>
      <species boundaryCondition="false" compartment="default" constant="false" hasOnlySubstanceUnits="false" id="species_6" initialConcentration="0" multi:speciesType="minerva_species_type_GenericProtein" name="PKA" sboTerm="SBO:0000252">
        <notes>
          <body xmlns="http://www.w3.org/1999/xhtml">
     <p/>
  </body>
        </notes>
        <annotation>
          <rdf:RDF xmlns:rdf="http://www.w3.org/1999/02/22-rdf-syntax-ns#" xmlns:dc="http://purl.org/dc/elements/1.1/" xmlns:dcterms="http://purl.org/dc/terms/" xmlns:vCard="http://www.w3.org/2001/vcard-rdf/3.0#" xmlns:bqbiol="http://biomodels.net/biology-qualifiers/" xmlns:bqmodel="http://biomodels.net/model-qualifiers/">
<rdf:Description rdf:about="#">
<dcterms:modified rdf:parseType="Resource"/>
</rdf:Description>
</rdf:RDF>
        </annotation>
              <multi:listOfSpeciesFeatures>
          <multi:speciesFeature xmlns:multi="http://www.sbml.org/sbml/level3/version1/multi/version1" multi:occur="1" multi:speciesFeatureType="minerva_structural_state_GenericProtein">
            <multi:listOfSpeciesFeatureValues>
              <multi:speciesFeatureValue multi:value="minerva_structural_state_GenericProtein_1052"/>
            </multi:listOfSpeciesFeatureValues>
          </multi:speciesFeature>
          <multi:speciesFeature xmlns:multi="http://www.sbml.org/sbml/level3/version1/multi/version1" multi:occur="1" multi:speciesFeatureType="minerva_position_to_compartment_GenericProtein">
            <multi:listOfSpeciesFeatureValues>
              <multi:speciesFeatureValue multi:value="minerva_position_to_compartment_GenericProtein_1047"/>
            </multi:listOfSpeciesFeatureValues>
          </multi:speciesFeature>
          <multi:speciesFeature xmlns:multi="http://www.sbml.org/sbml/level3/version1/multi/version1" multi:occur="1" multi:speciesFeatureType="minerva_activity_GenericProtein">
            <multi:listOfSpeciesFeatureValues>
              <multi:speciesFeatureValue multi:value="minerva_activity_GenericProtein_1048"/>
            </multi:listOfSpeciesFeatureValues>
          </multi:speciesFeature>
        </multi:listOfSpeciesFeatures>
      </species>
      <species boundaryCondition="false" compartment="default" constant="false" hasOnlySubstanceUnits="false" id="species_7" initialConcentration="0" multi:speciesType="minerva_species_type_GenericProtein" name="GPI" sboTerm="SBO:0000252">
        <notes>
          <body xmlns="http://www.w3.org/1999/xhtml">
     <p/>
  </body>
        </notes>
        <annotation>
          <rdf:RDF xmlns:rdf="http://www.w3.org/1999/02/22-rdf-syntax-ns#" xmlns:dc="http://purl.org/dc/elements/1.1/" xmlns:dcterms="http://purl.org/dc/terms/" xmlns:vCard="http://www.w3.org/2001/vcard-rdf/3.0#" xmlns:bqbiol="http://biomodels.net/biology-qualifiers/" xmlns:bqmodel="http://biomodels.net/model-qualifiers/">
<rdf:Description rdf:about="#">
<dcterms:modified rdf:parseType="Resource"/>
</rdf:Description>
</rdf:RDF>
        </annotation>
              <multi:listOfSpeciesFeatures>
          <multi:speciesFeature xmlns:multi="http://www.sbml.org/sbml/level3/version1/multi/version1" multi:occur="1" multi:speciesFeatureType="minerva_position_to_compartment_GenericProtein">
            <multi:listOfSpeciesFeatureValues>
              <multi:speciesFeatureValue multi:value="minerva_position_to_compartment_GenericProtein_1047"/>
            </multi:listOfSpeciesFeatureValues>
          </multi:speciesFeature>
          <multi:speciesFeature xmlns:multi="http://www.sbml.org/sbml/level3/version1/multi/version1" multi:occur="1" multi:speciesFeatureType="minerva_activity_GenericProtein">
            <multi:listOfSpeciesFeatureValues>
              <multi:speciesFeatureValue multi:value="minerva_activity_GenericProtein_1048"/>
            </multi:listOfSpeciesFeatureValues>
          </multi:speciesFeature>
        </multi:listOfSpeciesFeatures>
      </species>
      <species boundaryCondition="false" compartment="default" constant="false" hasOnlySubstanceUnits="false" id="species_8" initialConcentration="0" multi:speciesType="minerva_species_type_GenericProtein" name="PFK1" sboTerm="SBO:0000252">
        <notes>
          <body xmlns="http://www.w3.org/1999/xhtml">
     <p/>
  </body>
        </notes>
        <annotation>
          <rdf:RDF xmlns:rdf="http://www.w3.org/1999/02/22-rdf-syntax-ns#" xmlns:dc="http://purl.org/dc/elements/1.1/" xmlns:dcterms="http://purl.org/dc/terms/" xmlns:vCard="http://www.w3.org/2001/vcard-rdf/3.0#" xmlns:bqbiol="http://biomodels.net/biology-qualifiers/" xmlns:bqmodel="http://biomodels.net/model-qualifiers/">
<rdf:Description rdf:about="#">
<dcterms:modified rdf:parseType="Resource"/>
</rdf:Description>
</rdf:RDF>
        </annotation>
              <multi:listOfSpeciesFeatures>
          <multi:speciesFeature xmlns:multi="http://www.sbml.org/sbml/level3/version1/multi/version1" multi:occur="1" multi:speciesFeatureType="minerva_position_to_compartment_GenericProtein">
            <multi:listOfSpeciesFeatureValues>
              <multi:speciesFeatureValue multi:value="minerva_position_to_compartment_GenericProtein_1047"/>
            </multi:listOfSpeciesFeatureValues>
          </multi:speciesFeature>
          <multi:speciesFeature xmlns:multi="http://www.sbml.org/sbml/level3/version1/multi/version1" multi:occur="1" multi:speciesFeatureType="minerva_activity_GenericProtein">
            <multi:listOfSpeciesFeatureValues>
              <multi:speciesFeatureValue multi:value="minerva_activity_GenericProtein_1048"/>
            </multi:listOfSpeciesFeatureValues>
          </multi:speciesFeature>
        </multi:listOfSpeciesFeatures>
      </species>
      <species boundaryCondition="false" compartment="default" constant="false" hasOnlySubstanceUnits="false" id="species_9" initialConcentration="0" multi:speciesType="minerva_species_type_GenericProtein" name="PFKFB2" sboTerm="SBO:0000252">
        <notes>
          <body xmlns="http://www.w3.org/1999/xhtml">
     <p/>
  </body>
        </notes>
        <annotation>
          <rdf:RDF xmlns:rdf="http://www.w3.org/1999/02/22-rdf-syntax-ns#" xmlns:dc="http://purl.org/dc/elements/1.1/" xmlns:dcterms="http://purl.org/dc/terms/" xmlns:vCard="http://www.w3.org/2001/vcard-rdf/3.0#" xmlns:bqbiol="http://biomodels.net/biology-qualifiers/" xmlns:bqmodel="http://biomodels.net/model-qualifiers/">
<rdf:Description rdf:about="#">
<dcterms:modified rdf:parseType="Resource"/>
</rdf:Description>
</rdf:RDF>
        </annotation>
              <multi:listOfSpeciesFeatures>
          <multi:speciesFeature xmlns:multi="http://www.sbml.org/sbml/level3/version1/multi/version1" multi:occur="1" multi:speciesFeatureType="minerva_position_to_compartment_GenericProtein">
            <multi:listOfSpeciesFeatureValues>
              <multi:speciesFeatureValue multi:value="minerva_position_to_compartment_GenericProtein_1047"/>
            </multi:listOfSpeciesFeatureValues>
          </multi:speciesFeature>
          <multi:speciesFeature xmlns:multi="http://www.sbml.org/sbml/level3/version1/multi/version1" multi:occur="1" multi:speciesFeatureType="minerva_modification_type_GenericProtein_Residue_PHOSPHORYLATED">
            <multi:listOfSpeciesFeatureValues>
              <multi:speciesFeatureValue id="modification_residue_1" multi:value="minerva_modification_type_GenericProtein_Residue_PHOSPHORYLATED_1053"/>
            </multi:listOfSpeciesFeatureValues>
          </multi:speciesFeature>
          <multi:speciesFeature xmlns:multi="http://www.sbml.org/sbml/level3/version1/multi/version1" multi:occur="1" multi:speciesFeatureType="minerva_activity_GenericProtein">
            <multi:listOfSpeciesFeatureValues>
              <multi:speciesFeatureValue multi:value="minerva_activity_GenericProtein_1048"/>
            </multi:listOfSpeciesFeatureValues>
          </multi:speciesFeature>
        </multi:listOfSpeciesFeatures>
      </species>
      <species boundaryCondition="false" compartment="default" constant="false" hasOnlySubstanceUnits="false" id="species_10" initialConcentration="0" multi:speciesType="minerva_species_type_SimpleMolecule" name="?-D-glucose-6P" sboTerm="SBO:0000247">
        <notes>
          <body xmlns="http://www.w3.org/1999/xhtml">
     <p/>
  </body>
        </notes>
        <annotation>
          <rdf:RDF xmlns:rdf="http://www.w3.org/1999/02/22-rdf-syntax-ns#" xmlns:dc="http://purl.org/dc/elements/1.1/" xmlns:dcterms="http://purl.org/dc/terms/" xmlns:vCard="http://www.w3.org/2001/vcard-rdf/3.0#" xmlns:bqbiol="http://biomodels.net/biology-qualifiers/" xmlns:bqmodel="http://biomodels.net/model-qualifiers/">
<rdf:Description rdf:about="#">
<dcterms:modified rdf:parseType="Resource"/>
</rdf:Description>
</rdf:RDF>
        </annotation>
              <multi:listOfSpeciesFeatures>
          <multi:speciesFeature xmlns:multi="http://www.sbml.org/sbml/level3/version1/multi/version1" multi:occur="1" multi:speciesFeatureType="minerva_position_to_compartment_SimpleMolecule">
            <multi:listOfSpeciesFeatureValues>
              <multi:speciesFeatureValue multi:value="minerva_position_to_compartment_SimpleMolecule_1049"/>
            </multi:listOfSpeciesFeatureValues>
          </multi:speciesFeature>
          <multi:speciesFeature xmlns:multi="http://www.sbml.org/sbml/level3/version1/multi/version1" multi:occur="1" multi:speciesFeatureType="minerva_activity_SimpleMolecule">
            <multi:listOfSpeciesFeatureValues>
              <multi:speciesFeatureValue multi:value="minerva_activity_SimpleMolecule_1050"/>
            </multi:listOfSpeciesFeatureValues>
          </multi:speciesFeature>
        </multi:listOfSpeciesFeatures>
      </species>
      <species boundaryCondition="false" compartment="default" constant="false" hasOnlySubstanceUnits="false" id="species_11" initialConcentration="0" multi:speciesType="minerva_species_type_SimpleMolecule" name="?-D-fructose-2,6P2" sboTerm="SBO:0000247">
        <notes>
          <body xmlns="http://www.w3.org/1999/xhtml">
     <p/>
  </body>
        </notes>
        <annotation>
          <rdf:RDF xmlns:rdf="http://www.w3.org/1999/02/22-rdf-syntax-ns#" xmlns:dc="http://purl.org/dc/elements/1.1/" xmlns:dcterms="http://purl.org/dc/terms/" xmlns:vCard="http://www.w3.org/2001/vcard-rdf/3.0#" xmlns:bqbiol="http://biomodels.net/biology-qualifiers/" xmlns:bqmodel="http://biomodels.net/model-qualifiers/">
<rdf:Description rdf:about="#">
<dcterms:modified rdf:parseType="Resource"/>
</rdf:Description>
</rdf:RDF>
        </annotation>
              <multi:listOfSpeciesFeatures>
          <multi:speciesFeature xmlns:multi="http://www.sbml.org/sbml/level3/version1/multi/version1" multi:occur="1" multi:speciesFeatureType="minerva_position_to_compartment_SimpleMolecule">
            <multi:listOfSpeciesFeatureValues>
              <multi:speciesFeatureValue multi:value="minerva_position_to_compartment_SimpleMolecule_1049"/>
            </multi:listOfSpeciesFeatureValues>
          </multi:speciesFeature>
          <multi:speciesFeature xmlns:multi="http://www.sbml.org/sbml/level3/version1/multi/version1" multi:occur="1" multi:speciesFeatureType="minerva_activity_SimpleMolecule">
            <multi:listOfSpeciesFeatureValues>
              <multi:speciesFeatureValue multi:value="minerva_activity_SimpleMolecule_1050"/>
            </multi:listOfSpeciesFeatureValues>
          </multi:speciesFeature>
        </multi:listOfSpeciesFeatures>
      </species>
    </listOfSpecies>
    <listOfReactions>
      <reaction id="glyph_n21" reversible="false" sboTerm="SBO:0000176">
        <notes>
          <body xmlns="http://www.w3.org/1999/xhtml">
     <p/>
  </body>
        </notes>
        <annotation>
          <rdf:RDF xmlns:rdf="http://www.w3.org/1999/02/22-rdf-syntax-ns#" xmlns:dc="http://purl.org/dc/elements/1.1/" xmlns:dcterms="http://purl.org/dc/terms/" xmlns:vCard="http://www.w3.org/2001/vcard-rdf/3.0#" xmlns:bqbiol="http://biomodels.net/biology-qualifiers/" xmlns:bqmodel="http://biomodels.net/model-qualifiers/">
<rdf:Description rdf:about="#">
<dcterms:modified rdf:parseType="Resource"/>
</rdf:Description>
</rdf:RDF>
        </annotation>
              <listOfReactants>
          <speciesReference constant="false" species="species_6"/>
        </listOfReactants>
        <listOfProducts>
          <speciesReference constant="false" species="species_0"/>
        </listOfProducts>
        <listOfModifiers>
          <modifierSpeciesReference sboTerm="SBO:0000459" species="species_5"/>
        </listOfModifiers>
      </reaction>
      <reaction id="glyph_n15" reversible="false" sboTerm="SBO:0000176">
        <notes>
          <body xmlns="http://www.w3.org/1999/xhtml">
     <p/>
  </body>
        </notes>
        <annotation>
          <rdf:RDF xmlns:rdf="http://www.w3.org/1999/02/22-rdf-syntax-ns#" xmlns:dc="http://purl.org/dc/elements/1.1/" xmlns:dcterms="http://purl.org/dc/terms/" xmlns:vCard="http://www.w3.org/2001/vcard-rdf/3.0#" xmlns:bqbiol="http://biomodels.net/biology-qualifiers/" xmlns:bqmodel="http://biomodels.net/model-qualifiers/">
<rdf:Description rdf:about="#">
<dcterms:modified rdf:parseType="Resource"/>
</rdf:Description>
</rdf:RDF>
        </annotation>
              <listOfReactants>
          <speciesReference constant="false" species="species_4"/>
        </listOfReactants>
        <listOfProducts>
          <speciesReference constant="false" species="species_9"/>
        </listOfProducts>
        <listOfModifiers>
          <modifierSpeciesReference sboTerm="SBO:0000013" species="species_0"/>
        </listOfModifiers>
      </reaction>
      <reaction id="glyph_n5" reversible="true" sboTerm="SBO:0000176">
        <notes>
          <body xmlns="http://www.w3.org/1999/xhtml">
     <p/>
  </body>
        </notes>
        <annotation>
          <rdf:RDF xmlns:rdf="http://www.w3.org/1999/02/22-rdf-syntax-ns#" xmlns:dc="http://purl.org/dc/elements/1.1/" xmlns:dcterms="http://purl.org/dc/terms/" xmlns:vCard="http://www.w3.org/2001/vcard-rdf/3.0#" xmlns:bqbiol="http://biomodels.net/biology-qualifiers/" xmlns:bqmodel="http://biomodels.net/model-qualifiers/">
<rdf:Description rdf:about="#">
<dcterms:modified rdf:parseType="Resource"/>
</rdf:Description>
</rdf:RDF>
        </annotation>
              <listOfReactants>
          <speciesReference constant="false" species="species_10"/>
        </listOfReactants>
        <listOfProducts>
          <speciesReference constant="false" species="species_1"/>
        </listOfProducts>
        <listOfModifiers>
          <modifierSpeciesReference sboTerm="SBO:0000013" species="species_7"/>
        </listOfModifiers>
      </reaction>
      <reaction id="glyph_n13" reversible="false" sboTerm="SBO:0000176">
        <notes>
          <body xmlns="http://www.w3.org/1999/xhtml">
     <p/>
  </body>
        </notes>
        <annotation>
          <rdf:RDF xmlns:rdf="http://www.w3.org/1999/02/22-rdf-syntax-ns#" xmlns:dc="http://purl.org/dc/elements/1.1/" xmlns:dcterms="http://purl.org/dc/terms/" xmlns:vCard="http://www.w3.org/2001/vcard-rdf/3.0#" xmlns:bqbiol="http://biomodels.net/biology-qualifiers/" xmlns:bqmodel="http://biomodels.net/model-qualifiers/">
<rdf:Description rdf:about="#">
<dcterms:modified rdf:parseType="Resource"/>
</rdf:Description>
</rdf:RDF>
        </annotation>
              <listOfReactants>
          <speciesReference constant="false" species="species_11"/>
        </listOfReactants>
        <listOfProducts>
          <speciesReference constant="false" species="species_1"/>
        </listOfProducts>
        <listOfModifiers>
          <modifierSpeciesReference sboTerm="SBO:0000013" species="species_9"/>
        </listOfModifiers>
      </reaction>
      <reaction id="glyph_n6" reversible="false" sboTerm="SBO:0000176">
        <notes>
          <body xmlns="http://www.w3.org/1999/xhtml">
     <p/>
  </body>
        </notes>
        <annotation>
          <rdf:RDF xmlns:rdf="http://www.w3.org/1999/02/22-rdf-syntax-ns#" xmlns:dc="http://purl.org/dc/elements/1.1/" xmlns:dcterms="http://purl.org/dc/terms/" xmlns:vCard="http://www.w3.org/2001/vcard-rdf/3.0#" xmlns:bqbiol="http://biomodels.net/biology-qualifiers/" xmlns:bqmodel="http://biomodels.net/model-qualifiers/">
<rdf:Description rdf:about="#">
<dcterms:modified rdf:parseType="Resource"/>
</rdf:Description>
</rdf:RDF>
        </annotation>
              <listOfReactants>
          <speciesReference constant="false" species="species_1"/>
        </listOfReactants>
        <listOfProducts>
          <speciesReference constant="false" species="species_3"/>
        </listOfProducts>
        <listOfModifiers>
          <modifierSpeciesReference sboTerm="SBO:0000013" species="species_8"/>
        </listOfModifiers>
      </reaction>
      <reaction id="glyph_n12" reversible="false" sboTerm="SBO:0000176">
        <notes>
          <body xmlns="http://www.w3.org/1999/xhtml">
     <p/>
  </body>
        </notes>
        <annotation>
          <rdf:RDF xmlns:rdf="http://www.w3.org/1999/02/22-rdf-syntax-ns#" xmlns:dc="http://purl.org/dc/elements/1.1/" xmlns:dcterms="http://purl.org/dc/terms/" xmlns:vCard="http://www.w3.org/2001/vcard-rdf/3.0#" xmlns:bqbiol="http://biomodels.net/biology-qualifiers/" xmlns:bqmodel="http://biomodels.net/model-qualifiers/">
<rdf:Description rdf:about="#">
<dcterms:modified rdf:parseType="Resource"/>
</rdf:Description>
</rdf:RDF>
        </annotation>
              <listOfReactants>
          <speciesReference constant="false" species="species_1"/>
        </listOfReactants>
        <listOfProducts>
          <speciesReference constant="false" species="species_11"/>
        </listOfProducts>
        <listOfModifiers>
          <modifierSpeciesReference sboTerm="SBO:0000013" species="species_4"/>
        </listOfModifiers>
      </reaction>
      <reaction id="glyph_n7" reversible="false" sboTerm="SBO:0000176">
        <notes>
          <body xmlns="http://www.w3.org/1999/xhtml">
     <p/>
  </body>
        </notes>
        <annotation>
          <rdf:RDF xmlns:rdf="http://www.w3.org/1999/02/22-rdf-syntax-ns#" xmlns:dc="http://purl.org/dc/elements/1.1/" xmlns:dcterms="http://purl.org/dc/terms/" xmlns:vCard="http://www.w3.org/2001/vcard-rdf/3.0#" xmlns:bqbiol="http://biomodels.net/biology-qualifiers/" xmlns:bqmodel="http://biomodels.net/model-qualifiers/">
<rdf:Description rdf:about="#">
<dcterms:modified rdf:parseType="Resource"/>
</rdf:Description>
</rdf:RDF>
        </annotation>
              <listOfReactants>
          <speciesReference constant="false" species="species_3"/>
        </listOfReactants>
        <listOfProducts>
          <speciesReference constant="false" species="species_1"/>
        </listOfProducts>
        <listOfModifiers>
          <modifierSpeciesReference sboTerm="SBO:0000013" species="species_2"/>
        </listOfModifiers>
      </reaction>
    </listOfReactions>
  </model>
</sbml>